teslaclient/__init__.py
teslaclient/teslaclient.py
teslaclient/vehicle.py
teslaclient-0.0.5.dist-info/LICENSE
teslaclient-0.0.5.dist-info/METADATA
teslaclient-0.0.5.dist-info/WHEEL
teslaclient-0.0.5.dist-info/top_level.txt
teslaclient-0.0.5.dist-info/RECORD
