Metadata-Version: 2.1
Name: teslaclient
Version: 0.0.5
Summary: Python Tesla API wrapper
Home-page: https://github.com/jshurak/tesla_client
Author: Jeff Shurak
Author-email: jshurak@gmail.com
License: UNKNOWN
Platform: UNKNOWN
Classifier: Programming Language :: Python :: 3
Classifier: License :: OSI Approved :: MIT License
Classifier: Operating System :: OS Independent
Requires-Python: >=3.7
